biodatasets/__init__.py
biodatasets/dataset.py
biodatasets/version.py
biodatasets/utils/__init__.py
biodatasets/utils/google_bucket.py
biodatasets/utils/logger.py
tests/__init__.py
tests/test_dataset.py
bio_datasets-0.0.4.dist-info/LICENSE
bio_datasets-0.0.4.dist-info/METADATA
bio_datasets-0.0.4.dist-info/WHEEL
bio_datasets-0.0.4.dist-info/top_level.txt
bio_datasets-0.0.4.dist-info/RECORD
