Metadata-Version: 2.1
Name: bio-datasets
Version: 0.0.4
Summary: Open-source collection of biology datasets and pre-trained embeddings.
Home-page: https://github.com/DeepChainBio/datasets
Author: InstaDeep
Author-email: a.delfosse@instadeep.com
License: Apache-2.0
Platform: UNKNOWN
Classifier: License :: OSI Approved :: Apache Software License
Classifier: Operating System :: OS Independent
Classifier: Programming Language :: Python :: 3.7
Classifier: Topic :: Scientific/Engineering :: Artificial Intelligence
Classifier: Topic :: Scientific/Engineering :: Bio-Informatics
Classifier: Topic :: Software Development
Requires-Python: >=3.7
Requires-Dist: google-cloud-storage (==1.37.1)
Requires-Dist: pandas (==1.2.4)
Requires-Dist: tqdm (==4.60.0)
